thom/__init__.py
thom/arxiv.py
thom/cli.py
thom/py.typed
thom/summarizer.py
thom-0.1.1.dist-info/METADATA
thom-0.1.1.dist-info/WHEEL
thom-0.1.1.dist-info/entry_points.txt
thom-0.1.1.dist-info/licenses/LICENSE
thom-0.1.1.dist-info/RECORD
