Metadata-Version: 2.4
Name: thom
Version: 0.1.1
Summary: Summarize research papers from arXiv using LLMs
Project-URL: Homepage, https://github.com/thom-project/thom
Project-URL: Documentation, https://github.com/thom-project/thom#readme
Project-URL: Repository, https://github.com/thom-project/thom
Project-URL: Issues, https://github.com/thom-project/thom/issues
Author: thom contributors
License-Expression: MIT
License-File: LICENSE
Keywords: ai,arxiv,llm,papers,research,science,summarization
Classifier: Development Status :: 3 - Alpha
Classifier: Intended Audience :: Developers
Classifier: Intended Audience :: Science/Research
Classifier: License :: OSI Approved :: MIT License
Classifier: Operating System :: OS Independent
Classifier: Programming Language :: Python :: 3
Classifier: Programming Language :: Python :: 3.10
Classifier: Programming Language :: Python :: 3.11
Classifier: Programming Language :: Python :: 3.12
Classifier: Topic :: Scientific/Engineering :: Artificial Intelligence
Classifier: Topic :: Text Processing :: General
Requires-Python: >=3.10
Requires-Dist: litellm>=1.0.0
Provides-Extra: dev
Requires-Dist: black>=23.0.0; extra == 'dev'
Requires-Dist: mypy>=1.0.0; extra == 'dev'
Requires-Dist: pytest-asyncio>=0.21.0; extra == 'dev'
Requires-Dist: pytest>=7.0.0; extra == 'dev'
Requires-Dist: ruff>=0.1.0; extra == 'dev'
